Workbook

Sheet Hoja1
A1: CONSTRUCCION DE ACERAS Y BORDILLOS
A3: NUMERO / ITEM | B3: CONCEPTO RUBRO | C3: UNIDAD | D3: CANTIDAD | E3: P.UNITARIO | F3: P.TOTAL
A4: 1 | B4: Limpieza y debroce de muro | C4: m2 | D4: =C19*C20 -> 2625 | F4: =ROUND(D4*E4,2) -> 0
A5: 2 | B5: Replanteo y nivelacion con equipo topografico | C5: m2 | D5: =C19*C20 -> 2625 | F5: =ROUND(D5*E5,2) -> 0
A6: 3 | B6: Excavacion a maquina | C6: m3 | D6: =(C19*C20*C21) -> 1050 | F6: =ROUND(D6*E6,2) -> 0
A7: 4 | B7: Relleno compactado con material del sitio e=0.20 m | C7: m3 | D7: =C19*C20*C22 -> 525 | F7: =ROUND(D7*E7,2) -> 0
A8: 5 | B8: Relleno compactado con mejoramineto con subase clase III ( e=0,30 m ) | C8: m3 | D8: =C19*C20*C23 -> 787.5 | F8: =ROUND(D8*E8,2) -> 0
A9: 6 | B9: Relleno a maquina con piedra bola bajo acera e=15 cm | C9: m3 | D9: =C19*C20*C24 -> 393.75 | F9: =ROUND(D9*E9,2) -> 0
A10: 7 | B10: Enconfrado de bordillo | C10: ml | D10: =C19 -> 1750 | F10: =ROUND(D10*E10,2) -> 0
A11: 8 | B11: Bordillo de hormigon simple (15 cm x 50 cm )F'c=210 kg/cm2 | C11: ml | D11: =C19 -> 1750 | F11: =ROUND(D11*E11,2) -> 0
A12: 9 | B12: Malla electrosoldada de (150x150*5) mm | C12: m2 | D12: =C19*C20 -> 2625 | F12: =ROUND(D12*E12,2) -> 0
A13: 10 | B13: Hormigon simple de F'c=210 kg/cm2 en acera e=10cm | C13: m2 | D13: =C19*C20 -> 2625 | F13: =ROUND(D13*E13,2) -> 0
E14: TOTAL
B16: Son:
B18: Datos
B19: L = 1750 m | C19: 1750 | D19: m
B20: ancho acera 1.5 | C20: 1.5 | D20: m
B21: H( escavacion) | C21: 0.4 | D21: m
B22: e sitio | C22: 0.2 | D22: m
B23: e subase | C23: 0.3 | D23: m
B24: e piedra bola | C24: 0.15 | D24: m

Sheet 1.
A1: ANALISIS DE PRECIOS UNITARIOS
A3: RUBRO: | G3: HOJA 1 DE 10
A4: =Hoja1!B4 -> Limpieza y debroce de muro | G4: CB-001
A5: DETALLE: | D5: RENDIMIENTO H/U | E5: 0.13 | F5: UNIDAD:
A7: EQUIPOS
A8: DESCRIPCION | C8: CANTIDAD | D8: TARIFA/HORA | E8: COSTO/HORA | F8: RENDIMIENTO | G8: COSTO
A9: Herramientas manuales ( 5% M.O ) | C9: 1 | D9: 5% DE MANO DE OBRA | F9: =E5 -> 0.13 | G9: =G24*5% -> 0.05642
E10: =D10*C10 -> 0 | F10: =E5 -> 0.13 | G10: =F10*E10 -> 0
F11: =E5 -> 0.13
F17: SUBTOTAL (M) | G17: =ROUND(SUM(G9:G16),5) -> 0.05642
A18: MANOS DE OBRA
A19: DESCRIPCION | C19: CANTIDAD | D19: JORNAL/HORA | E19: COSTO/HORA | F19: RENDIMIENTO | G19: COSTO
A20: Peon | C20: 2 | D20: 4.34 | E20: =D20*C20 -> 8.68 | F20: =E5 -> 0.13 | G20: =F20*E20 -> 1.1284
E21: =D21*C21 -> 0 | F21: =E6 -> 0 | G21: =F21*E21 -> 0
E22: =D22*C22 -> 0 | F22: =E7 -> 0 | G22: =F22*E22 -> 0
F24: SUBTOTAL (N) | G24: =ROUND(SUM(G20:G22),5) -> 1.1284
A25: MATERIALES
A26: DESCRIPCION | D26: UNIDAD | E26: CANTIDAD | F26: P.UNITARIO | G26: COSTO
G27: =F27*E27 -> 0
G28: =F28*E28 -> 0
G29: =F29*E29 -> 0
F33: SUBTOTAL (O) | G33: =ROUND(SUM(G27:G32),5) -> 0
A34: TRANSPORTE
A35: DESCRIPCION | D35: UNIDAD | E35: CANTIDAD | F35: TARIFA | G35: COSTO
F38: SUBTOTAL (P)
A39: Estos precios no incluyen IVA
D40: TOTAL COSTOS DIRECTOS (M+N+O+P) | G40: =ROUND((G17+G24+G33+G38),2) -> 1.18
D41: INDIRECTOS Y UTILIDAD | F41: 0.25 | G41: =ROUND((G40*F41),2) -> 0.3
D42: OTROS INDIRECTOS
A45: KARLA JAMILETH MOREIRA | D45: COSTO TOTAL DEL RUBRO | G45: =ROUND((G41+G40),2) -> 1.48
A46: OFERENTE | D46: VALOR OFERTADO | G46: =G45 -> 1.48

Sheet 2
A1: ANALISIS DE PRECIOS UNITARIOS
A3: RUBRO: | G3: HOJA 2 DE 10
A4: =Hoja1!B5 -> Replanteo y nivelacion con equipo topografico | G4: CB-001
A5: DETALLE: | D5: RENDIMIENTO H/U | E5: 0.1 | F5: UNIDAD: | G5: =Hoja1!C5 -> m2
A7: EQUIPOS
A8: DESCRIPCION | C8: CANTIDAD | D8: TARIFA/HORA | E8: COSTO/HORA | F8: RENDIMIENTO | G8: COSTO
A9: Herramientas manuales ( 5% M.O ) | C9: 1 | D9: 5% DE MANO DE OBRA | F9: =E5 -> 0.1 | G9: =G24*5% -> 0.068
A10: Teodolito | C10: 1 | D10: 2.5 | E10: =D10*C10 -> 2.5 | F10: =E5 -> 0.1 | G10: =F10*E10 -> 0.25
F11: =E5 -> 0.1
F17: SUBTOTAL (M) | G17: =ROUND(SUM(G9:G16),5) -> 0.318
A18: MANOS DE OBRA
A19: DESCRIPCION | C19: CANTIDAD | D19: JORNAL/HORA | E19: COSTO/HORA | F19: RENDIMIENTO | G19: COSTO
A20: peon | C20: 1 | D20: 4.34 | E20: =D20*C20 -> 4.34 | F20: =E5 -> 0.1 | G20: =F20*E20 -> 0.434
A21: Topografo | C21: 1 | D21: 4.87 | E21: =D21*C21 -> 4.87 | F21: =E5 -> 0.1 | G21: =F21*E21 -> 0.487
A22: Cadenero | C22: 1 | D22: 4.39 | E22: =D22*C22 -> 4.39 | F22: =E5 -> 0.1 | G22: =F22*E22 -> 0.439
F24: SUBTOTAL (N) | G24: =ROUND(SUM(G20:G22),5) -> 1.36
A25: MATERIALES
A26: DESCRIPCION | D26: UNIDAD | E26: CANTIDAD | F26: P.UNITARIO | G26: COSTO
A27: Estacas | D27: unidad | E27: 0.1 | F27: 0.2 | G27: =F27*E27 -> 0.02
A28: Clavos | D28: kg | E28: 0.01 | F28: 1.5 | G28: =F28*E28 -> 0.015
A29: Pinturas | D29: lt | E29: 0.01 | F29: 4.25 | G29: =F29*E29 -> 0.0425
F33: SUBTOTAL (O) | G33: =ROUND(SUM(G27:G32),5) -> 0.0775
A34: TRANSPORTE
A35: DESCRIPCION | D35: UNIDAD | E35: CANTIDAD | F35: TARIFA | G35: COSTO
F38: SUBTOTAL (P)
A39: Estos precios no incluyen IVA
D40: TOTAL COSTOS DIRECTOS (M+N+O+P) | G40: =ROUND((G17+G24+G33+G38),2) -> 1.76
D41: INDIRECTOS Y UTILIDAD | F41: 0.25 | G41: =ROUND((G40*F41),2) -> 0.44
D42: OTROS INDIRECTOS
A45: KARLA JAMILETH MOREIRA | D45: COSTO TOTAL DEL RUBRO | G45: =ROUND((G41+G40),2) -> 2.2
A46: OFERENTE | D46: VALOR OFERTADO | G46: =G45 -> 2.2

Sheet 3
A1: ANALISIS DE PRECIOS UNITARIOS
A3: RUBRO: | G3: HOJA 2 DE 10
A4: =Hoja1!B6 -> Excavacion a maquina | G4: CB-001
A5: DETALLE: | D5: RENDIMIENTO H/U | E5: 0.1 | F5: UNIDAD: | G5: =Hoja1!C6 -> m3
A7: EQUIPOS
A8: DESCRIPCION | C8: CANTIDAD | D8: TARIFA/HORA | E8: COSTO/HORA | F8: RENDIMIENTO | G8: COSTO
A9: Herramientas manuales ( 5% M.O ) | C9: 1 | D9: 5% DE MANO DE OBRA | F9: =E5 -> 0.1 | G9: =G24*5% -> 0.068
A10: Retroexcavadora | C10: 1 | D10: 25 | E10: =D10*C10 -> 25 | F10: =E5 -> 0.1 | G10: =F10*E10 -> 2.5
F11: =E5 -> 0.1
F17: SUBTOTAL (M) | G17: =ROUND(SUM(G9:G16),5) -> 2.568
A18: MANOS DE OBRA
A19: DESCRIPCION | C19: CANTIDAD | D19: JORNAL/HORA | E19: COSTO/HORA | F19: RENDIMIENTO | G19: COSTO
A20: Operador de retroexcavadora | C20: 1 | D20: 4.87 | E20: =D20*C20 -> 4.87 | F20: =E5 -> 0.1 | G20: =F20*E20 -> 0.487
A21: Engrasador o abastecedor responsable | C21: 1 | D21: 4.39 | E21: =D21*C21 -> 4.39 | F21: =E5 -> 0.1 | G21: =F21*E21 -> 0.439
A22: Peon | C22: 1 | D22: 4.34 | E22: =D22*C22 -> 4.34 | F22: =E5 -> 0.1 | G22: =F22*E22 -> 0.434
F24: SUBTOTAL (N) | G24: =ROUND(SUM(G20:G22),5) -> 1.36
A25: MATERIALES
A26: DESCRIPCION | D26: UNIDAD | E26: CANTIDAD | F26: P.UNITARIO | G26: COSTO
G27: =F27*E27 -> 0
G28: =F28*E28 -> 0
G29: =F29*E29 -> 0
F33: SUBTOTAL (O) | G33: =ROUND(SUM(G27:G32),5) -> 0
A34: TRANSPORTE
A35: DESCRIPCION | D35: UNIDAD | E35: CANTIDAD | F35: TARIFA | G35: COSTO
F38: SUBTOTAL (P)
A39: Estos precios no incluyen IVA
D40: TOTAL COSTOS DIRECTOS (M+N+O+P) | G40: =ROUND((G17+G24+G33+G38),2) -> 3.93
D41: INDIRECTOS Y UTILIDAD | F41: 0.25 | G41: =ROUND((G40*F41),2) -> 0.98
D42: OTROS INDIRECTOS
A45: KARLA JAMILETH MOREIRA | D45: COSTO TOTAL DEL RUBRO | G45: =ROUND((G41+G40),2) -> 4.91
A46: OFERENTE | D46: VALOR OFERTADO | G46: =G45 -> 4.91

Sheet 4
A1: ANALISIS DE PRECIOS UNITARIOS
A3: RUBRO: | G3: HOJA 2 DE 10
A4: =Hoja1!B7 -> Relleno compactado con material del sitio e=0.20 m | G4: CB-001
A5: DETALLE: | D5: RENDIMIENTO H/U | E5: 0.25 | F5: UNIDAD: | G5: =Hoja1!C7 -> m3
A7: EQUIPOS
A8: DESCRIPCION | C8: CANTIDAD | D8: TARIFA/HORA | E8: COSTO/HORA | F8: RENDIMIENTO | G8: COSTO
A9: Herramientas manuales ( 5% M.O ) | C9: 1 | D9: 5% DE MANO DE OBRA | F9: =E5 -> 0.25 | G9: =G24*5% -> 0.163375
A10: vibroplsnador manual | C10: 1 | D10: 5 | E10: =D10*C10 -> 5 | F10: =E5 -> 0.25 | G10: =F10*E10 -> 1.25
F11: =E5 -> 0.25
F17: SUBTOTAL (M) | G17: =ROUND(SUM(G9:G16),5) -> 1.41338
A18: MANOS DE OBRA
A19: DESCRIPCION | C19: CANTIDAD | D19: JORNAL/HORA | E19: COSTO/HORA | F19: RENDIMIENTO | G19: COSTO
A20: operador de equipo liviano | C20: 1 | D20: 4.39 | E20: =D20*C20 -> 4.39 | F20: =E5 -> 0.25 | G20: =F20*E20 -> 1.0975
A21: Peon | C21: 2 | D21: 4.34 | E21: =D21*C21 -> 8.68 | F21: =E5 -> 0.25 | G21: =F21*E21 -> 2.17
E22: =D22*C22 -> 0 | F22: =E5 -> 0.25 | G22: =F22*E22 -> 0
F24: SUBTOTAL (N) | G24: =ROUND(SUM(G20:G22),5) -> 3.2675
A25: MATERIALES
A26: DESCRIPCION | D26: UNIDAD | E26: CANTIDAD | F26: P.UNITARIO | G26: COSTO
A27: mejoramiento | D27: m3 | E27: 1.2 | F27: 5 | G27: =F27*E27 -> 6
A28: agua | D28: lt | E28: 0.1 | F28: 1 | G28: =F28*E28 -> 0.1
G29: =F29*E29 -> 0
F33: SUBTOTAL (O) | G33: =ROUND(SUM(G27:G32),5) -> 6.1
A34: TRANSPORTE
A35: DESCRIPCION | D35: UNIDAD | E35: CANTIDAD | F35: TARIFA | G35: COSTO
F38: SUBTOTAL (P)
A39: Estos precios no incluyen IVA
D40: TOTAL COSTOS DIRECTOS (M+N+O+P) | G40: =ROUND((G17+G24+G33+G38),2) -> 10.78
D41: INDIRECTOS Y UTILIDAD | F41: 0.25 | G41: =ROUND((G40*F41),2) -> 2.7
D42: OTROS INDIRECTOS
A45: KARLA JAMILETH MOREIRA | D45: COSTO TOTAL DEL RUBRO | G45: =ROUND((G41+G40),2) -> 13.48
A46: OFERENTE | D46: VALOR OFERTADO | G46: =G45 -> 13.48

Sheet 5
A1: ANALISIS DE PRECIOS UNITARIOS
A3: RUBRO: | G3: HOJA 2 DE 10
A4: =Hoja1!B8 -> Relleno compactado con mejoramineto con subase clase III ( e=0,30 m ) | G4: CB-001
A5: DETALLE: | D5: RENDIMIENTO H/U | E5: 0.25 | F5: UNIDAD: | G5: =Hoja1!C8 -> m3
A7: EQUIPOS
A8: DESCRIPCION | C8: CANTIDAD | D8: TARIFA/HORA | E8: COSTO/HORA | F8: RENDIMIENTO | G8: COSTO
A9: Herramientas manuales ( 5% M.O ) | C9: 1 | D9: 5% DE MANO DE OBRA | F9: =E5 -> 0.25 | G9: =G24*5% -> 0.163375
A10: vibroplanador manual | C10: 1 | D10: 5 | E10: =D10*C10 -> 5 | F10: =E5 -> 0.25 | G10: =F10*E10 -> 1.25
F11: =E5 -> 0.25
F17: SUBTOTAL (M) | G17: =ROUND(SUM(G9:G16),5) -> 1.41338
A18: MANOS DE OBRA
A19: DESCRIPCION | C19: CANTIDAD | D19: JORNAL/HORA | E19: COSTO/HORA | F19: RENDIMIENTO | G19: COSTO
A20: operador de equipos liviano | C20: 1 | D20: 4.39 | E20: =D20*C20 -> 4.39 | F20: =E5 -> 0.25 | G20: =F20*E20 -> 1.0975
A21: peon | C21: 2 | D21: 4.34 | E21: =D21*C21 -> 8.68 | F21: =E5 -> 0.25 | G21: =F21*E21 -> 2.17
E22: =D22*C22 -> 0 | F22: =E5 -> 0.25 | G22: =F22*E22 -> 0
F24: SUBTOTAL (N) | G24: =ROUND(SUM(G20:G22),5) -> 3.2675
A25: MATERIALES
A26: DESCRIPCION | D26: UNIDAD | E26: CANTIDAD | F26: P.UNITARIO | G26: COSTO
A27: agua | D27: lt | E27: 50 | F27: 0.01 | G27: =F27*E27 -> 0.5
A28: subase clase 3 | D28: m3 | E28: 1.2 | F28: 7.34 | G28: =F28*E28 -> 8.808
G29: =F29*E29 -> 0
F33: SUBTOTAL (O) | G33: =ROUND(SUM(G27:G32),5) -> 9.308
A34: TRANSPORTE
A35: DESCRIPCION | D35: UNIDAD | E35: CANTIDAD | F35: TARIFA | G35: COSTO
F38: SUBTOTAL (P)
A39: Estos precios no incluyen IVA
D40: TOTAL COSTOS DIRECTOS (M+N+O+P) | G40: =ROUND((G17+G24+G33+G38),2) -> 13.99
D41: INDIRECTOS Y UTILIDAD | F41: 0.25 | G41: =ROUND((G40*F41),2) -> 3.5
D42: OTROS INDIRECTOS
A45: KARLA JAMILETH MOREIRA | D45: COSTO TOTAL DEL RUBRO | G45: =ROUND((G41+G40),2) -> 17.49
A46: OFERENTE | D46: VALOR OFERTADO | G46: =G45 -> 17.49

Sheet 6
A1: ANALISIS DE PRECIOS UNITARIOS
A3: RUBRO: | G3: HOJA 2 DE 10
A4: =Hoja1!B9 -> Relleno a maquina con piedra bola bajo acera e=15 cm | G4: CB-001
A5: DETALLE: | D5: RENDIMIENTO H/U | E5: 0.07 | F5: UNIDAD: | G5: =Hoja1!C9 -> m3
A7: EQUIPOS
A8: DESCRIPCION | C8: CANTIDAD | D8: TARIFA/HORA | E8: COSTO/HORA | F8: RENDIMIENTO | G8: COSTO
A9: Herramientas manuales ( 5% M.O ) | C9: 1 | D9: 5% DE MANO DE OBRA | F9: =E5 -> 0.07 | G9: =G24*5% -> 0.0339395
A10: Retroexcavadora 125 hp | C10: 1 | D10: 45 | E10: =D10*C10 -> 45 | F10: =E5 -> 0.07 | G10: =F10*E10 -> 3.15
F11: =E5 -> 0.07
F17: SUBTOTAL (M) | G17: =ROUND(SUM(G9:G16),5) -> 3.18394
A18: MANOS DE OBRA
A19: DESCRIPCION | C19: CANTIDAD | D19: JORNAL/HORA | E19: COSTO/HORA | F19: RENDIMIENTO | G19: COSTO
A20: operador de retoexcavadora | C20: 1 | D20: 4.87 | E20: =D20*C20 -> 4.87 | F20: =E5 -> 0.07 | G20: =F20*E20 -> 0.3409
A21: peon | C21: 1 | D21: 4.34 | E21: =D21*C21 -> 4.34 | F21: =E5 -> 0.07 | G21: =F21*E21 -> 0.3038
A22: maestro mayor | C22: 0.1 | D22: 4.87 | E22: =D22*C22 -> 0.487 | F22: =E5 -> 0.07 | G22: =F22*E22 -> 0.03409
F24: SUBTOTAL (N) | G24: =ROUND(SUM(G20:G22),5) -> 0.67879
A25: MATERIALES
A26: DESCRIPCION | D26: UNIDAD | E26: CANTIDAD | F26: P.UNITARIO | G26: COSTO
A27: piedra bola de 10 cm | E27: 1.2 | F27: 8 | G27: =F27*E27 -> 9.6
G28: =F28*E28 -> 0
G29: =F29*E29 -> 0
F33: SUBTOTAL (O) | G33: =ROUND(SUM(G27:G32),5) -> 9.6
A34: TRANSPORTE
A35: DESCRIPCION | D35: UNIDAD | E35: CANTIDAD | F35: TARIFA | G35: COSTO
F38: SUBTOTAL (P)
A39: Estos precios no incluyen IVA
D40: TOTAL COSTOS DIRECTOS (M+N+O+P) | G40: =ROUND((G17+G24+G33+G38),2) -> 13.46
D41: INDIRECTOS Y UTILIDAD | F41: 0.25 | G41: =ROUND((G40*F41),2) -> 3.37
D42: OTROS INDIRECTOS
A45: KARLA JAMILETH MOREIRA | D45: COSTO TOTAL DEL RUBRO | G45: =ROUND((G41+G40),2) -> 16.83
A46: OFERENTE | D46: VALOR OFERTADO | G46: =G45 -> 16.83

Sheet 7
A1: ANALISIS DE PRECIOS UNITARIOS
A3: RUBRO: | G3: HOJA 2 DE 10
A4: =Hoja1!B10 -> Enconfrado de bordillo | G4: CB-001
A5: DETALLE: | D5: RENDIMIENTO H/U | E5: 0.05 | F5: UNIDAD: | G5: =Hoja1!C10 -> ml
A7: EQUIPOS
A8: DESCRIPCION | C8: CANTIDAD | D8: TARIFA/HORA | E8: COSTO/HORA | F8: RENDIMIENTO | G8: COSTO
A9: Herramientas manuales ( 5% M.O ) | C9: 1 | D9: 5% DE MANO DE OBRA | F9: =E5 -> 0.05 | G9: =G24*5% -> 0.032675
E10: =D10*C10 -> 0 | F10: =E5 -> 0.05 | G10: =F10*E10 -> 0
F11: =E5 -> 0.05
F17: SUBTOTAL (M) | G17: =ROUND(SUM(G9:G16),5) -> 0.03268
A18: MANOS DE OBRA
A19: DESCRIPCION | C19: CANTIDAD | D19: JORNAL/HORA | E19: COSTO/HORA | F19: RENDIMIENTO | G19: COSTO
A20: albañil | C20: 1 | D20: 4.39 | E20: =D20*C20 -> 4.39 | F20: =E5 -> 0.05 | G20: =F20*E20 -> 0.2195
A21: peon | C21: 2 | D21: 4.34 | E21: =D21*C21 -> 8.68 | F21: =E5 -> 0.05 | G21: =F21*E21 -> 0.434
E22: =D22*C22 -> 0 | F22: =E7 -> 0 | G22: =F22*E22 -> 0
F24: SUBTOTAL (N) | G24: =ROUND(SUM(G20:G22),5) -> 0.6535
A25: MATERIALES
A26: DESCRIPCION | D26: UNIDAD | E26: CANTIDAD | F26: P.UNITARIO | G26: COSTO
A27: encofrado metalico segun diseño | D27: ml | E27: 1 | F27: 1 | G27: =F27*E27 -> 1
G28: =F28*E28 -> 0
G29: =F29*E29 -> 0
F33: SUBTOTAL (O) | G33: =ROUND(SUM(G27:G32),5) -> 1
A34: TRANSPORTE
A35: DESCRIPCION | D35: UNIDAD | E35: CANTIDAD | F35: TARIFA | G35: COSTO
F38: SUBTOTAL (P)
A39: Estos precios no incluyen IVA
D40: TOTAL COSTOS DIRECTOS (M+N+O+P) | G40: =ROUND((G17+G24+G33+G38),2) -> 1.69
D41: INDIRECTOS Y UTILIDAD | F41: 0.25 | G41: =ROUND((G40*F41),2) -> 0.42
D42: OTROS INDIRECTOS
A45: KARLA JAMILETH MOREIRA | D45: COSTO TOTAL DEL RUBRO | G45: =ROUND((G41+G40),2) -> 2.11
A46: OFERENTE | D46: VALOR OFERTADO | G46: =G45 -> 2.11

Sheet 8
A1: ANALISIS DE PRECIOS UNITARIOS
A3: RUBRO: | G3: HOJA 2 DE 10
A4: =Hoja1!B11 -> Bordillo de hormigon simple (15 cm x 50 cm )F'c=210 kg/cm2 | G4: CB-001
A5: DETALLE: | D5: RENDIMIENTO H/U | E5: 0.2 | F5: UNIDAD:
A7: EQUIPOS
A8: DESCRIPCION | C8: CANTIDAD | D8: TARIFA/HORA | E8: COSTO/HORA | F8: RENDIMIENTO | G8: COSTO
A9: Herramientas manuales ( 5% M.O ) | C9: 1 | D9: 5% DE MANO DE OBRA | F9: =E5 -> 0.2 | G9: =G24*5% -> 0.40084
A10: concretera de 1 saco | C10: 1 | D10: 6 | E10: =D10*C10 -> 6 | F10: =E5 -> 0.2 | G10: =F10*E10 -> 1.2
A11: vibrador | C11: 1 | D11: 4 | E11: =D11*C11 -> 4 | F11: =E5 -> 0.2 | G11: =E11*F11 -> 0.8
F17: SUBTOTAL (M) | G17: =ROUND(SUM(G9:G16),5) -> 2.40084
A18: MANOS DE OBRA
A19: DESCRIPCION | C19: CANTIDAD | D19: JORNAL/HORA | E19: COSTO/HORA | F19: RENDIMIENTO | G19: COSTO
A20: albañil | C20: 1 | D20: 4.39 | E20: =D20*C20 -> 4.39 | F20: =E5 -> 0.2 | G20: =F20*E20 -> 0.878
A21: peon | C21: 8 | D21: 4.34 | E21: =D21*C21 -> 34.72 | F21: =E5 -> 0.2 | G21: =F21*E21 -> 6.944
A22: maestro mayor | C22: 0.2 | D22: 4.87 | E22: =D22*C22 -> 0.974 | F22: =E5 -> 0.2 | G22: =F22*E22 -> 0.1948
F24: SUBTOTAL (N) | G24: =ROUND(SUM(G20:G22),5) -> 8.0168
A25: MATERIALES
A26: DESCRIPCION | D26: UNIDAD | E26: CANTIDAD | F26: P.UNITARIO | G26: COSTO
A27: cemento | E27: 26.25 | F27: 0.2 | G27: =F27*E27 -> 5.25
A28: arena | E28: 0.045 | F28: 10 | G28: =F28*E28 -> 0.45
A29: grava | E29: 0.068 | F29: 15 | G29: =F29*E29 -> 1.02
E30: 20 | F30: 0.01 | G30: =F30*E30 -> 0.2
F33: SUBTOTAL (O) | G33: =ROUND(SUM(G27:G32),5) -> 6.92
A34: TRANSPORTE
A35: DESCRIPCION | D35: UNIDAD | E35: CANTIDAD | F35: TARIFA | G35: COSTO
F38: SUBTOTAL (P)
A39: Estos precios no incluyen IVA
D40: TOTAL COSTOS DIRECTOS (M+N+O+P) | G40: =ROUND((G17+G24+G33+G38),2) -> 17.34
D41: INDIRECTOS Y UTILIDAD | F41: 0.25 | G41: =ROUND((G40*F41),2) -> 4.34
D42: OTROS INDIRECTOS
A45: KARLA JAMILETH MOREIRA | D45: COSTO TOTAL DEL RUBRO | G45: =ROUND((G41+G40),2) -> 21.68
A46: OFERENTE | D46: VALOR OFERTADO | G46: =G45 -> 21.68

Sheet 9
A1: ANALISIS DE PRECIOS UNITARIOS
A3: RUBRO: | G3: HOJA 2 DE 10
G4: CB-001
A5: DETALLE: | D5: RENDIMIENTO H/U | E5: 0.05 | F5: UNIDAD:
A7: EQUIPOS
A8: DESCRIPCION | C8: CANTIDAD | D8: TARIFA/HORA | E8: COSTO/HORA | F8: RENDIMIENTO | G8: COSTO
A9: Herramientas manuales ( 5% M.O ) | C9: 1 | D9: 5% DE MANO DE OBRA | F9: =E5 -> 0.05 | G9: =G24*5% -> 0.0163375
A10: amoladora manual | C10: 1 | D10: 0.5 | E10: =D10*C10 -> 0.5 | F10: =E5 -> 0.05 | G10: =F10*E10 -> 0.025
F11: =E5 -> 0.05
F17: SUBTOTAL (M) | G17: =ROUND(SUM(G9:G16),5) -> 0.04134
A18: MANOS DE OBRA
A19: DESCRIPCION | C19: CANTIDAD | D19: JORNAL/HORA | E19: COSTO/HORA | F19: RENDIMIENTO | G19: COSTO
A20: peon | C20: 1 | D20: 4.34 | E20: =D20*C20 -> 4.34 | F20: =E5 -> 0.05 | G20: =F20*E20 -> 0.217
A21: albañil | C21: 0.5 | D21: 4.39 | E21: =D21*C21 -> 2.195 | F21: =E5 -> 0.05 | G21: =F21*E21 -> 0.10975
E22: =D22*C22 -> 0 | F22: =E7 -> 0 | G22: =F22*E22 -> 0
F24: SUBTOTAL (N) | G24: =ROUND(SUM(G20:G22),5) -> 0.32675
A25: MATERIALES
A26: DESCRIPCION | D26: UNIDAD | E26: CANTIDAD | F26: P.UNITARIO | G26: COSTO
A27: malla electrosoldada 15x15x5 mm | D27: m2 | E27: 1.05 | F27: 3.5 | G27: =F27*E27 -> 3.675
G28: =F28*E28 -> 0
G29: =F29*E29 -> 0
F33: SUBTOTAL (O) | G33: =ROUND(SUM(G27:G32),5) -> 3.675
A34: TRANSPORTE
A35: DESCRIPCION | D35: UNIDAD | E35: CANTIDAD | F35: TARIFA | G35: COSTO
F38: SUBTOTAL (P)
A39: Estos precios no incluyen IVA
D40: TOTAL COSTOS DIRECTOS (M+N+O+P) | G40: =ROUND((G17+G24+G33+G38),2) -> 4.04
D41: INDIRECTOS Y UTILIDAD | F41: 0.25 | G41: =ROUND((G40*F41),2) -> 1.01
D42: OTROS INDIRECTOS
A45: KARLA JAMILETH MOREIRA | D45: COSTO TOTAL DEL RUBRO | G45: =ROUND((G41+G40),2) -> 5.05
A46: OFERENTE | D46: VALOR OFERTADO | G46: =G45 -> 5.05

Sheet 10
A1: ANALISIS DE PRECIOS UNITARIOS
A3: RUBRO: | G3: HOJA 2 DE 10
G4: CB-001
A5: DETALLE: | D5: RENDIMIENTO H/U | E5: 0.2 | F5: UNIDAD:
A7: EQUIPOS
A8: DESCRIPCION | C8: CANTIDAD | D8: TARIFA/HORA | E8: COSTO/HORA | F8: RENDIMIENTO | G8: COSTO
A9: Herramientas manuales ( 5% M.O ) | C9: 1 | D9: 5% DE MANO DE OBRA | F9: =E5 -> 0.2 | G9: =G24*5% -> 0.40084
A10: concretera de 1 saco | C10: 1 | D10: 5 | E10: =D10*C10 -> 5 | F10: =E5 -> 0.2 | G10: =F10*E10 -> 1
F11: =E5 -> 0.2
F17: SUBTOTAL (M) | G17: =ROUND(SUM(G9:G16),5) -> 1.40084
A18: MANOS DE OBRA
A19: DESCRIPCION | C19: CANTIDAD | D19: JORNAL/HORA | E19: COSTO/HORA | F19: RENDIMIENTO | G19: COSTO
C20: 8 | D20: 4.34 | E20: =D20*C20 -> 34.72 | F20: =E5 -> 0.2 | G20: =F20*E20 -> 6.944
C21: 0.2 | D21: 4.87 | E21: =D21*C21 -> 0.974 | F21: =E5 -> 0.2 | G21: =F21*E21 -> 0.1948
A22: albañil | C22: 1 | D22: 4.39 | E22: =D22*C22 -> 4.39 | F22: =E5 -> 0.2 | G22: =F22*E22 -> 0.878
F24: SUBTOTAL (N) | G24: =ROUND(SUM(G20:G22),5) -> 8.0168
A25: MATERIALES
A26: DESCRIPCION | D26: UNIDAD | E26: CANTIDAD | F26: P.UNITARIO | G26: COSTO
A27: cemento | E27: 35 | F27: 0.2 | G27: =F27*E27 -> 7
A28: arena | E28: 0.09 | F28: 15 | G28: =F28*E28 -> 1.35
A29: grava | E29: 0.06 | F29: 10 | G29: =F29*E29 -> 0.6
A30: agua | E30: 20 | F30: 0.01 | G30: =E30*F30 -> 0.2
A31: tiras | E31: 0.47 | F31: 1.5 | G31: =E31*F31 -> 0.705
A32: aditivos | E32: 0.3 | F32: 1.5 | G32: =E32*F32 -> 0.45
F33: SUBTOTAL (O) | G33: =ROUND(SUM(G27:G32),5) -> 10.305
A34: TRANSPORTE
A35: DESCRIPCION | D35: UNIDAD | E35: CANTIDAD | F35: TARIFA | G35: COSTO
F38: SUBTOTAL (P)
A39: Estos precios no incluyen IVA
D40: TOTAL COSTOS DIRECTOS (M+N+O+P) | G40: =ROUND((G17+G24+G33+G38),2) -> 19.72
D41: INDIRECTOS Y UTILIDAD | F41: 0.25 | G41: =ROUND((G40*F41),2) -> 4.93
D42: OTROS INDIRECTOS
A45: KARLA JAMILETH MOREIRA | D45: COSTO TOTAL DEL RUBRO | G45: =ROUND((G41+G40),2) -> 24.65
A46: OFERENTE | D46: VALOR OFERTADO | G46: =G45 -> 24.65

Sheet Hoja2
